{
  "activists": [
    {
      "complexity_1": [
        {
          "question": "Много мусора. Купить улучшение для перерабатывающей станции?",
          "answers": {
            "yes": "Да",
            "no": "Нет"
          },
          "yes": {
            "worker_fatigue": 0,
            "environments": 10,
            "money": -20,
            "answer": "Красавчик)), респект"
          },
          "no": {
            "worker_fatigue": 0,
            "environments": 10,
            "money": 0,
            "answer": "Реально, ну и пох, зачем это, - респект, природу надо беречь"
          }
        },
        {
          "question": "Как вы думаете, имеет ли влияние человечество на состояние природы?",
          "answers": {
            "yes": "конечно, очень сильное",
            "no": "абсолютного никакого"
          },
          "yes": {
            "worker_fatigue": 0,
            "environments": 10,
            "money": 0,
            "answer": "Вы правы, природа - это главный ресурс земли, его нужно использовать с умом"
          },
          "no": {
            "worker_fatigue": 0,
            "environments": -10,
            "money": 0,
            "answer": "Серьёзно????, природа - это главный ресурс земли, его нужно использовать с умом"
          }
        },
        {
          "question": "Ваши рабочие много жалуются на плотный график, уменьшить скорость завода?",
          "answers": {
            "yes": "Да",
            "no": "Нет"
          },
          "yes": {
            "worker_fatigue": -10,
            "environments": 10,
            "money": -10
          },
          "no": {
            "worker_fatigue": 10,
            "environments": -10,
            "money": 10,
            "answer": "емаё, что со станками"
          }
        },
        {
          "question": "Говорят, что на вашем заводе есть крысы, сделать хим. чистку завода?",
          "answers": {
            "yes": "Да",
            "no": "Нет"
          },
          "yes": {
            "worker_fatigue": 10,
            "environments": 10,
            "money": -10,
            "answer": "емаё, что со станками, зачем вы это сделали?"
          },
          "no": {
            "worker_fatigue": -10,
            "environments": -10,
            "money": 10,
            "answer": "емаё, что со станками, зачем вы это сделали?"
          }
        },
        {
          "question": "Правда, что начальство хочет вас заменить?",
          "answers": {
            "yes": "Да, конечно, я уже стар, скоро в отставку",
            "no": "Нет, это всё враньё"
          },
          "yes": {
            "worker_fatigue": -5,
            "environments": 0,
            "money": -10,
            "answer": "Ваши акции резко упали на 10 процентов(, зарплаты сотрудников упали тоже"
          },
          "no": {
            "worker_fatigue": 0,
            "environments": 0,
            "money": 0,
            "answer": "На этот ответ не было комментариев"
          }
        },
        {
          "question": "Хм, есть ощущение, что кто-то крыса(ворует часы(деньги)), сделать проверку?",
          "answers": {
            "yes": "Да",
            "no": "Нет"
          },
          "yes": {
            "worker_fatigue": -10,
            "environments": 0,
            "money": -5,
            "answer": "Рабочие недовольны, просят добавку"
          },
          "no": {
            "worker_fatigue": 5,
            "environments": 0,
            "money": -10,
            "answer": "Повезло повезло"
          }
        },
        {
          "question": "Бунт, мы заметили у вас не уплату налогов, заплатить налоги?",
          "answers": {
            "yes": "Да",
            "no": "Нет"
          },
          "yes": {
            "worker_fatigue": 0,
            "environments": 0,
            "money": -10,
            "answer": "ХАХ, мы над вами пошутили, спасибо за копейку))"
          },
          "no": {
            "worker_fatigue": 5,
            "environments": 0,
            "money": 5,
            "answer": "Это была ошибка, извините"
          }
        },
        {
          "question": "Через 10мин приедет проверка, примите меры",
          "answers": {
            "yes": "Убраться на заводе",
            "no": "Пох"
          },
          "yes": {
            "worker_fatigue": 0,
            "environments": 0,
            "money": -10,
            "answer": "Повезло, эти люди просто проверили офис, а ты мог убраться и заранее"
          },
          "no": {
            "worker_fatigue": 5,
            "environments": 0,
            "money": 5,
            "answer": "Тебе не повезло(, штраф"
          }
        },
        {
          "question": "Сработала пожарная сигнализация, вывести персонал?",
          "answers": {
            "yes": "Да",
            "no": "Нет"
          },
          "yes": {
            "worker_fatigue": 0,
            "environments": 5,
            "money": -10,
            "answer": "В этой ситуации тебе повезло, никто не пострадал, завод остановлен на две недели, зарплаты рабочим по графику"
          },
          "no": {
            "worker_fatigue": -15,
            "environments": 5,
            "money": -15,
            "answer": "Да...., ты потерял 4 человек(, ты выплатил деньги их семьям + потерял бизнес на две недели("
          }
        },
        {
          "question": "По новостям рабочие утверждают, что они отдыхают на работе, увеличить скорость завода?",
          "answers": {
            "yes": "Да",
            "no": "Нет"
          },
          "yes": {
            "worker_fatigue": -5,
            "environments": -5,
            "money": 10,
            "answer": "Отлично, вы вышли на новый уровень скорости завода, всё хорошо, но рабочим сложно( "
          },
          "no": {
            "worker_fatigue": 0,
            "environments": 0,
            "money": -10,
            "answer": "Ну и ладно, ваш завод уходит в минус, вы ничего не зарабатываете"
          }
        }
      ],
      "complexity_2": [
        {
          "question": "Ходит слух, что сотрудники завода болеют астмой из-за пыли на заводе, провести медицинский осмотр?",
          "answers": {
            "yes": "Да",
            "no": "Нет"
          },
          "yes": {
            "worker_fatigue": 5,
            "environments": 0,
            "money": -5,
            "answer": "Оказалось, что часть сотрудников болеет, они на больничном"
          },
          "no": {
            "worker_fatigue": -15,
            "environments": 3,
            "money": -15,
            "answer": "Через недели половина завода начали болеть, производство остановилось"
          }
        },
        {
          "question": "Ваш завод закрывается из-за выброса плохих веществ в атмосферу, это правда?",
          "answers": {
            "yes": "Да",
            "no": "Нет, срочно поставить новые очистные фильтры"
          },
          "yes": {
            "worker_fatigue": 5,
            "environments": 0,
            "money": 5,
            "answer": "Финансирование города вам помогло, ваш завод продолжает работу"
          },
          "no": {
            "worker_fatigue": 0,
            "environments": 5,
            "money": 20,
            "answer": "Вы поставили новые фильтры за два дня и потратили очень много денег("
          }
        },
        {
          "question": "Ваш завод закрывается из-за выброса плохих веществ в атмосферу, это правда?",
          "answers": {
            "yes": "Да",
            "no": "Нет, срочно поставить новые очистные фильтры"
          },
          "yes": {
            "worker_fatigue": 5,
            "environments": 0,
            "money": 5,
            "answer": "Финансирование города вам помогло, ваш завод продолжает работу"
          },
          "no": {
            "worker_fatigue": 0,
            "environments": 5,
            "money": 20,
            "answer": "Вы поставили новые фильтры за два дня и потратили очень много денег("
          }
        },
        {
          "question": "У вас не чистая форма персонала, купить новую форму?",
          "answers": {
            "yes": "Да",
            "no": "Нет"
          },
          "yes": {
            "worker_fatigue": 10,
            "environments": -5,
            "money": -5,
            "answer": "Респект, рабочие довольный"
          },
          "no": {
            "worker_fatigue": -10,
            "environments": 0,
            "money": 0,
            "answer": "... не повезло не повезло, хотелось новую форму("
          }
        },
        {
          "question": "Говорят, что на заводе вашему рабочему отрезало палец из-за старого станка?",
          "answers": {
            "yes": "Купить новые станки",
            "no": "Починить старые"
          },
          "yes": {
            "worker_fatigue": 10,
            "environments": -10,
            "money": -15,
            "answer": "Респект, рабочие довольный"
          },
          "no": {
            "worker_fatigue": 5,
            "environments": -5,
            "money": -10,
            "answer": "Жаль..."
          }
        }
      ],
      "complexity_3": [
        {
          "question": "(Пришла налоговая) Ваш завод нелегально работает, либо все деньги, либо суд...",
          "answers": {
            "yes": "Платить",
            "no": "Пох..."
          },
          "yes": {
            "worker_fatigue": 0,
            "environments": 0,
            "money": -50,
            "answer": "Повезло повезло"
          },
          "no": {
            "worker_fatigue": -50,
            "environments": 0,
            "money": -100,
            "answer": "Вас посадили в тюрьму. Game over... restart....NO... error..."
          }
        },
        {
          "question": "Началась пандемия, рабочие начали болеть, сидеть на карантине, скорость завода падает, акции уменьшаются. Повысить зп? ",
          "answers": {
            "yes": "Да",
            "no": "Нет"
          },
          "yes": {
            "worker_fatigue": -30,
            "environments": -5,
            "money": -50,
            "answer": "Завод начал работу, но перестал приносить деньги"
          },
          "no": {
            "worker_fatigue": -10,
            "environments": 0,
            "money": -30,
            "answer": "Ваш завод получает минимум, но рабочие успевают выздороветь"
          }
        }
      ]
    }
  ]
}




